{
    "type":"wmslayer",
    "url":"http://paikkatieto.ymparisto.fi/ArcGis/services/INSPIRE/SYKE_Ortoilmakuvat/MapServer/WMSServer",
    "name":"Image2000mosaiikki",
    "organization": "Syke",
    "inspiretheme": "Backgrounds",
    "locale": {
        "fi": {
            "name": "Image2000mosaiikki"
        },
        "sv": {
            "name": "Image2000mosaiikki"
        },
        "en": {
            "name": "Image2000mosaiikki"
        }
    },
    "role_permissions": {
        "Guest" : ["VIEW_LAYER", "VIEW_PUBLISHED"],
        "User" : ["VIEW_LAYER", "VIEW_PUBLISHED", "PUBLISH"]
    },
	"metadataid": "3c80ee05-8597-4e80-a5a1-bd9e1db771be"
}
